glmdisc/__init__.py
glmdisc/_bestFormula.py
glmdisc/_discreteData.py
glmdisc/_discretize.py
glmdisc/_discretizeDummy.py
glmdisc/_fit.py
glmdisc/_fitNN.py
glmdisc/_fitSEM.py
glmdisc/_generateData.py
glmdisc/_gini_utils.py
glmdisc/_plot.py
glmdisc/_predict.py
glmdisc-0.1.2.data/scripts/consistency.py
glmdisc-0.1.2.data/scripts/factor_levels.py
glmdisc-0.1.2.data/scripts/linearity.py
glmdisc-0.1.2.dist-info/LICENSE
glmdisc-0.1.2.dist-info/METADATA
glmdisc-0.1.2.dist-info/WHEEL
glmdisc-0.1.2.dist-info/top_level.txt
glmdisc-0.1.2.dist-info/RECORD
