Metadata-Version: 2.1
Name: glmdisc
Version: 0.1.2
Summary: Feature quantization for parsimonious and interpretable models
Home-page: https://adimajo.github.io/glmdisc_python
Author: Adrien Ehrhardt
Author-email: adrien.ehrhardt@centraliens-lille.org
License: UNKNOWN
Keywords: discretization logistic regression levels grouping
Platform: UNKNOWN
Classifier: Development Status :: 4 - Beta
Classifier: Intended Audience :: Science/Research
Classifier: Topic :: Scientific/Engineering :: Artificial Intelligence
Classifier: License :: OSI Approved :: GNU General Public License v3 (GPLv3)
Classifier: Programming Language :: Python :: 3
Classifier: Programming Language :: Python :: 3 :: Only
Classifier: Programming Language :: Python :: 3.7
Classifier: Programming Language :: Python :: 3.8
Requires-Dist: scikit-learn (>=0.21.2)
Requires-Dist: numpy (>=1.16.4)
Requires-Dist: scipy (>=1.3.1)
Requires-Dist: pandas (>=0.25.1)
Requires-Dist: pygam (>=0.8.0)
Requires-Dist: matplotlib (>=3.2)
Requires-Dist: loguru
Requires-Dist: tensorflow (>=2.2.1)
Requires-Dist: livelossplot
Requires-Dist: ipykernel
Requires-Dist: bokeh
Provides-Extra: dev
Requires-Dist: pytest ; extra == 'dev'
Requires-Dist: coverage ; extra == 'dev'
Requires-Dist: sphinx ; extra == 'dev'
Requires-Dist: sphinx-rtd-theme ; extra == 'dev'
Requires-Dist: flake8 ; extra == 'dev'
Requires-Dist: pipenv-setup ; extra == 'dev'
Requires-Dist: numpydoc ; extra == 'dev'
Requires-Dist: wheel ; extra == 'dev'
Requires-Dist: codecov ; extra == 'dev'
Requires-Dist: twine ; extra == 'dev'
Requires-Dist: tox ; extra == 'dev'
Requires-Dist: tox-pyenv ; extra == 'dev'
Requires-Dist: hyperas ; extra == 'dev'
Requires-Dist: hyperopt ; extra == 'dev'
